LICENSE
README.md
setup.cfg
setup.py
dynamic_dispatch/__init__.py
dynamic_dispatch/_class.py
dynamic_dispatch/_func.py
dynamic_dispatch/_typeguard.py
dynamic_dispatch.egg-info/PKG-INFO
dynamic_dispatch.egg-info/SOURCES.txt
dynamic_dispatch.egg-info/dependency_links.txt
dynamic_dispatch.egg-info/requires.txt
dynamic_dispatch.egg-info/top_level.txt