Metadata-Version: 2.1
Name: dynamic-dispatch
Version: 1.0.2
Summary: dynamic dispatch decorator for classes and functions
Home-page: https://github.com/XevoInc/dynamic_dispatch
Author: Ryan Rowe
Author-email: rrowe@xevo.com
License: Apache License, Version 2.0
Platform: UNKNOWN
Classifier: Development Status :: 4 - Beta
Classifier: Intended Audience :: Developers
Classifier: License :: OSI Approved :: Apache Software License
Classifier: Programming Language :: Python
Classifier: Programming Language :: Python :: 3.7
Classifier: Programming Language :: Python :: 3.8
Classifier: Topic :: Utilities
Classifier: Typing :: Typed
Provides-Extra: typeguard
Provides-Extra: dev
